hypline/__init__.py
hypline/cli.py
hypline/enums.py
hypline/regression.py
hypline/schemas.py
hypline/utils.py
hypline-0.2.5.dist-info/METADATA
hypline-0.2.5.dist-info/WHEEL
hypline-0.2.5.dist-info/entry_points.txt
hypline-0.2.5.dist-info/licenses/LICENSE
hypline-0.2.5.dist-info/RECORD
