Metadata-Version: 2.4
Name: hypline
Version: 0.2.5
Summary: Data Cleaning and Analysis Pipeline for Hyperscanning Research
Project-URL: Repository, https://github.com/princeton-ddss/hypline
Project-URL: Documentation, https://princeton-ddss.github.io/hypline/latest/
Author-email: Sangyoon Park <datumvitae@gmail.com>
License-File: LICENSE
Requires-Python: >=3.10
Requires-Dist: dill>=0.3.9
Requires-Dist: nibabel>=5.3.2
Requires-Dist: nilearn>=0.11.1
Requires-Dist: numpy>=2.2.4
Requires-Dist: polars>=1.26.0
Requires-Dist: pydantic>=2.10.6
Requires-Dist: pyyaml>=6.0.2
Requires-Dist: rich>=14.0.0
Requires-Dist: typer>=0.15.2
